tree_interval/__init__.py
tree_interval/core/__init__.py
tree_interval/core/ast_builder.py
tree_interval/core/ast_types.py
tree_interval/core/frame_analyzer.py
tree_interval/core/future.py
tree_interval/core/interval_core.py
tree_interval/rich_printer/__init__.py
tree_interval/rich_printer/config.py
tree_interval/rich_printer/printer.py
tree_interval/visualizer/__init__.py
tree_interval/visualizer/config.py
tree_interval/visualizer/visualizer.py
tree_interval-0.1.34.dist-info/LICENSE
tree_interval-0.1.34.dist-info/METADATA
tree_interval-0.1.34.dist-info/WHEEL
tree_interval-0.1.34.dist-info/top_level.txt
tree_interval-0.1.34.dist-info/RECORD
