Metadata-Version: 2.1
Name: tree-interval
Version: 0.1.34
Summary: A Python package for managing and visualizing interval tree structures
Home-page: https://github.com/kairos-xx/tree-interval
Author: Joao Lopes
Author-email: Joao Lopes <joaoslopes@gmail.com>
License: 
Project-URL: Homepage, https://github.com/kairos-xx/tree-interval
Project-URL: Repository, https://github.com/kairos-xx/tree-interval.git
Classifier: Development Status :: 5 - Production/Stable
Classifier: Intended Audience :: Developers
Classifier: Intended Audience :: Science/Research
Classifier: License :: OSI Approved :: MIT License
Classifier: Programming Language :: Python :: 3
Classifier: Programming Language :: Python :: 3.11
Classifier: Topic :: Software Development :: Libraries :: Python Modules
Classifier: Topic :: Software Development :: Code Generators
Classifier: Topic :: Software Development :: Debuggers
Classifier: Operating System :: OS Independent
Classifier: Natural Language :: English
Classifier: Typing :: Typed
Requires-Python: >=3.11
License-File: LICENSE
